p1/transition_detector.v
// transition_detector.v
// ECE 303 HW 3 Problem 1 - Moore FSM transition detector
//
// `out` is held high for one clock whenever `in` changes from one clock to
// the next.  Realization: 2 D-flip-flops + 1 XOR gate.
//   Q1_next = in
//   Q0_next = in ^ Q1     (transition flag for the just-taken edge)
//   out     = Q0
//
// State encoding {Q1, Q0}:
//   S0 = 2'b00 : last in = 0, no transition  (out = 0)
//   S1 = 2'b01 : last in = 0, 1->0 transition (out = 1)
//   S2 = 2'b10 : last in = 1, no transition  (out = 0)
//   S3 = 2'b11 : last in = 1, 0->1 transition (out = 1)
//
// Active-low asynchronous reset puts the FSM in S0 with the input assumed 0
// until the first post-reset clock cycle (per the HW3 spec).

`timescale 1ns / 1ps

module transition_detector (
    input  wire clk,
    input  wire rstb,
    input  wire in,
    output wire out
);

    reg Q1, Q0;

    always @(posedge clk or negedge rstb) begin
        if (!rstb) begin
            Q1 <= 1'b0;
            Q0 <= 1'b0;
        end else begin
            Q1 <= in;
            Q0 <= in ^ Q1;
        end
    end

    assign out = Q0;

endmodule

p1/transition_detector_tb.v
// transition_detector_tb.v
// ECE 303 HW 3 Problem 1 - Testbench
//
// Drives the 9-bit sequence shown in the HW3 PDF (in = 0 1 1 0 0 1 0 1 1)
// plus one trailing 0 so the final 1->0 transition is visible.  Prints a
// per-cycle log of {rstb, in, out, Q1, Q0} and dumps a VCD for SimVision.
//
// Sim clock: 10 ns period (readability only -- synthesis target is 0.5 ns).
// Stimulus changes on the negedge so values are stable at the next posedge.

`timescale 1ns / 1ps

module transition_detector_tb;

    reg  clk;
    reg  rstb;
    reg  in;
    wire out;

    transition_detector dut (
        .clk  (clk),
        .rstb (rstb),
        .in   (in),
        .out  (out)
    );

    initial clk = 1'b0;
    always #5 clk = ~clk;

    initial begin
        $dumpfile("transition_detector_tb.vcd");
        $dumpvars(0, transition_detector_tb);

        $display("  time | rstb | in | out | Q1 Q0");
        $display("-------+------+----+-----+------");
        $monitor("%6t |  %b   | %b  |  %b  |  %b  %b",
                 $time, rstb, in, out, dut.Q1, dut.Q0);

        rstb = 1'b0;
        in   = 1'b0;

        // Release reset on a negedge so the first post-reset posedge sees in=0
        @(negedge clk) rstb = 1'b1;

        // 9-cycle PDF sequence: 0 1 1 0 0 1 0 1 1
        // (the first 0 is the implicit post-reset cycle; subsequent values are
        // driven here)
        @(negedge clk) in = 1'b1;   // cycle 2
        @(negedge clk) in = 1'b1;   // cycle 3
        @(negedge clk) in = 1'b0;   // cycle 4
        @(negedge clk) in = 1'b0;   // cycle 5
        @(negedge clk) in = 1'b1;   // cycle 6
        @(negedge clk) in = 1'b0;   // cycle 7
        @(negedge clk) in = 1'b1;   // cycle 8
        @(negedge clk) in = 1'b1;   // cycle 9
        @(negedge clk) in = 1'b0;   // trailing: shows final 1->0 transition
        @(negedge clk);
        #5 $finish;
    end

endmodule

p1/transition_detector_tb.vcd
$date
    May 25, 2026  11:23:27
$end
$version
    TOOL:	xmsim	18.09-s011
$end
$timescale
    1 ps
$end

$scope module transition_detector_tb $end
$var reg       1 !    clk $end
$var reg       1 "    rstb $end
$var reg       1 #    in $end
$var wire      1 $    out  $end

$scope module dut $end
$var wire      1 %    clk  $end
$var wire      1 &    rstb  $end
$var wire      1 '    in  $end
$var wire      1 $    out  $end
$var reg       1 (    Q1 $end
$var reg       1 )    Q0 $end
$upscope $end

$upscope $end

$enddefinitions $end
$dumpvars
0!
0"
0#
0$
0%
0&
0'
0(
0)
$end
#5000
1!
1%
#10000
0!
1"
1&
0%
#15000
1!
1%
#20000
0!
1#
1'
0%
#25000
1!
1%
1(
1)
1$
#30000
0!
0%
#35000
1!
1%
0)
0$
#40000
0!
0#
0'
0%
#45000
1!
1%
0(
1)
1$
#50000
0!
0%
#55000
1!
1%
0)
0$
#60000
0!
1#
1'
0%
#65000
1!
1%
1(
1)
1$
#70000
0!
0#
0'
0%
#75000
1!
1%
0(
#80000
0!
1#
1'
0%
#85000
1!
1%
1(
#90000
0!
0%
#95000
1!
1%
0)
0$
#100000
0!
0#
0'
0%
#105000
1!
1%
0(
1)
1$
